patch_fixer/__init__.py
patch_fixer/cli.py
patch_fixer/patch_fixer.py
patch_fixer/split.py
patch_fixer-0.4.1.dist-info/licenses/LICENSE
patch_fixer-0.4.1.dist-info/METADATA
patch_fixer-0.4.1.dist-info/WHEEL
patch_fixer-0.4.1.dist-info/entry_points.txt
patch_fixer-0.4.1.dist-info/top_level.txt
patch_fixer-0.4.1.dist-info/RECORD
