Metadata-Version: 2.4
Name: patch-fixer
Version: 0.4.1
Summary: Fixes erroneous git apply patches to the best of its ability.
Maintainer-email: Alex Mueller <amueller474@gmail.com>
License-Expression: Apache-2.0
Project-URL: Homepage, https://github.com/ajcm474/patch-fixer
Project-URL: Issues, https://github.com/ajcm474/patch-fixer/issues
Classifier: Development Status :: 3 - Alpha
Classifier: Intended Audience :: Developers
Classifier: Programming Language :: Python
Classifier: Programming Language :: Python :: 3
Classifier: Programming Language :: Python :: 3.10
Classifier: Programming Language :: Python :: 3.11
Classifier: Programming Language :: Python :: 3.12
Classifier: Programming Language :: Python :: 3.13
Classifier: Programming Language :: Python :: 3.14
Classifier: Programming Language :: Python :: 3 :: Only
Classifier: Topic :: Software Development
Requires-Python: >=3.10
License-File: LICENSE
Requires-Dist: GitPython
Provides-Extra: test
Requires-Dist: hypothesis; extra == "test"
Requires-Dist: pytest; extra == "test"
Requires-Dist: requests; extra == "test"
Dynamic: license-file
